scythe/__init__.py
scythe/adapters/__init__.py
scythe/adapters/base.py
scythe/ase.py
scythe/base.py
scythe/crystal_structure.py
scythe/csv.py
scythe/dft.py
scythe/electron_microscopy.py
scythe/file.py
scythe/filename.py
scythe/image.py
scythe/json.py
scythe/schemas/electron_microscopy.json
scythe/schemas/file.json
scythe/tdb.py
scythe/testing.py
scythe/utils/__init__.py
scythe/utils/grouping.py
scythe/utils/interface.py
scythe/version.py
scythe/xml.py
scythe/yaml.py
scythe_extractors-0.1.1.dist-info/entry_points.txt
scythe_extractors-0.1.1.dist-info/METADATA
scythe_extractors-0.1.1.dist-info/LICENSE
scythe_extractors-0.1.1.dist-info/WHEEL
scythe_extractors-0.1.1.dist-info/RECORD
